{
  "topic": "向量",
  "version": "2.0.0",
  "lastUpdated": "2025-11-25",
  "nodes": [
    {
      "id": "v1.1",
      "name": "向量的意義",
      "description": "向量與純量的差異、有向線段表示、向量相等的條件",
      "category": "基礎觀念",
      "level": 1,
      "prerequisites": [],
      "related": [],
      "tags": ["向量基礎", "定義", "有向線段"],
      "examples": ["ex_v1_1_1", "ex_v1_1_2"]
    },
    {
      "id": "v1.2",
      "name": "向量的表示法",
      "description": "幾何表示 $\\vec{AB}$、符號表示 $\\vec{a}$、坐標表示 $(x, y)$、基底向量 $\\hat{i}, \\hat{j}$",
      "category": "基礎觀念",
      "level": 1,
      "prerequisites": ["v1.1"],
      "related": [],
      "tags": ["向量基礎", "坐標", "基底向量"],
      "examples": ["ex_v1_2_1", "ex_v1_2_2"]
    },
    {
      "id": "v1.3",
      "name": "向量的長度",
      "description": "向量長度公式 $|\\vec{a}| = \\sqrt{x^2 + y^2}$，與畢氏定理的關係",
      "category": "基礎觀念",
      "level": 1,
      "prerequisites": ["v1.2"],
      "related": [],
      "tags": ["向量基礎", "長度", "畢氏定理"],
      "examples": ["ex_v1_3_1", "ex_v1_3_2", "ex_v1_3_3"]
    },
    {
      "id": "v1.4",
      "name": "零向量與單位向量",
      "description": "零向量 $\\vec{0}$ 的特性、單位向量定義、向量單位化 $\\hat{a} = \\frac{\\vec{a}}{|\\vec{a}|}$",
      "category": "基礎觀念",
      "level": 1,
      "prerequisites": ["v1.3"],
      "related": [],
      "tags": ["向量基礎", "單位向量", "零向量"],
      "examples": ["ex_v1_4_1", "ex_v1_4_2"]
    },
    {
      "id": "v2.1",
      "name": "向量的加法",
      "description": "三角形法則、平行四邊形法則、坐標運算、交換律與結合律",
      "category": "核心概念",
      "level": 2,
      "prerequisites": ["v1.2"],
      "related": [],
      "tags": ["向量運算", "加法", "平行四邊形"],
      "examples": ["ex_v2_1_1", "ex_v2_1_2", "ex_v2_1_3"]
    },
    {
      "id": "v2.2",
      "name": "向量的減法",
      "description": "幾何意義（終點指向起點）、坐標運算、兩點間向量 $\\vec{AB} = \\vec{OB} - \\vec{OA}$",
      "category": "核心概念",
      "level": 2,
      "prerequisites": ["v2.1"],
      "related": [],
      "tags": ["向量運算", "減法"],
      "examples": ["ex_v2_2_1", "ex_v2_2_2"]
    },
    {
      "id": "v2.3",
      "name": "純量積（數乘）",
      "description": "$k\\vec{a} = (kx, ky)$，改變長度，$k<0$ 時反向，分配律",
      "category": "核心概念",
      "level": 2,
      "prerequisites": ["v1.3"],
      "related": [],
      "tags": ["向量運算", "純量積", "數乘"],
      "examples": ["ex_v2_3_1", "ex_v2_3_2"]
    },
    {
      "id": "v2.4",
      "name": "向量的線性組合",
      "description": "$\\vec{c} = m\\vec{a} + n\\vec{b}$，基底與坐標系概念",
      "category": "核心概念",
      "level": 2,
      "prerequisites": ["v2.1", "v2.3"],
      "related": [],
      "tags": ["向量運算", "線性組合", "基底"],
      "examples": ["ex_v2_4_1"]
    },
    {
      "id": "v2.5",
      "name": "向量平行與共線",
      "description": "平行條件 $\\vec{a} = k\\vec{b}$，三點共線判定",
      "category": "核心概念",
      "level": 2,
      "prerequisites": ["v2.3"],
      "related": [],
      "tags": ["向量關係", "平行", "共線"],
      "examples": ["ex_v2_5_1", "ex_v2_5_2"]
    },
    {
      "id": "v2.6",
      "name": "分點公式",
      "description": "內分點 $\\vec{OP} = \\frac{n\\vec{OA} + m\\vec{OB}}{m+n}$，外分點公式，重心中點應用",
      "category": "核心概念",
      "level": 2,
      "prerequisites": ["v2.1", "v2.3"],
      "related": [],
      "tags": ["向量應用", "分點", "重心"],
      "examples": ["ex_v2_6_1", "ex_v2_6_2", "ex_v2_6_3"]
    },
    {
      "id": "v2.7",
      "name": "向量方程式（直線）",
      "description": "二維平面直線的向量方程式、參數式、點斜式與向量的關係",
      "category": "核心概念",
      "level": 2,
      "prerequisites": ["v2.1", "v2.3"],
      "related": ["v4.7"],
      "tags": ["向量方程式", "直線"],
      "examples": ["ex_v2_7_1", "ex_v2_7_2"]
    },
    {
      "id": "v2.8",
      "name": "向量不等式",
      "description": "三角不等式 $|\\vec{a} + \\vec{b}| \\leq |\\vec{a}| + \\vec{b}|$，等號成立條件",
      "category": "核心概念",
      "level": 2,
      "prerequisites": ["v1.3", "v2.1"],
      "related": ["v3.6"],
      "tags": ["不等式", "三角不等式"],
      "examples": ["ex_v2_8_1", "ex_v2_8_2"]
    },
    {
      "id": "v3.9",
      "name": "複數與向量",
      "description": "複數平面表示、複數與向量的對應關係、極式與向量",
      "category": "進階應用",
      "level": 3,
      "prerequisites": ["v1.2", "v3.3"],
      "related": ["v1.3"],
      "tags": ["複數", "極坐標"],
      "examples": ["ex_v3_9_1", "ex_v3_9_2"]
    },
    {
      "id": "v3.10",
      "name": "極坐標與向量",
      "description": "極坐標表示 $(r, \\theta)$、與直角坐標轉換、極式單位向量",
      "category": "進階應用",
      "level": 3,
      "prerequisites": ["v1.2", "v3.3"],
      "related": ["v3.9"],
      "tags": ["極坐標", "坐標轉換"],
      "examples": ["ex_v3_10_1", "ex_v3_10_2"]
    },
    {
      "id": "v4.10",
      "name": "向量微積分基礎",
      "description": "向量函數 $\\vec{r}(t)$、速度向量 $\\vec{v} = \\frac{d\\vec{r}}{dt}$、加速度向量",
      "category": "整合應用",
      "level": 4,
      "prerequisites": ["v2.1", "v6.2"],
      "related": ["v6.1"],
      "tags": ["微積分", "向量函數", "導數"],
      "examples": ["ex_v4_10_1", "ex_v4_10_2"]
    },
    {
      "id": "v3.1",
      "name": "向量內積",
      "description": "內積定義 $\\vec{a} \\cdot \\vec{b} = |\\vec{a}||\\vec{b}|\\cos\\theta = x_1x_2 + y_1y_2$",
      "category": "進階應用",
      "level": 3,
      "prerequisites": ["v1.3", "v2.1"],
      "related": [],
      "tags": ["內積", "點積"],
      "examples": ["ex_v3_1_1", "ex_v3_1_2", "ex_v3_1_3"]
    },
    {
      "id": "v3.2",
      "name": "內積的性質",
      "description": "交換律、分配律、$\\vec{a} \\cdot \\vec{a} = |\\vec{a}|^2$",
      "category": "進階應用",
      "level": 3,
      "prerequisites": ["v3.1"],
      "related": [],
      "tags": ["內積", "運算性質"],
      "examples": ["ex_v3_2_1"]
    },
    {
      "id": "v3.3",
      "name": "向量夾角",
      "description": "用內積求夾角，銳角鈍角直角判定，方向角與方向餘弦",
      "category": "進階應用",
      "level": 3,
      "prerequisites": ["v3.1"],
      "related": [],
      "tags": ["夾角", "三角函數"],
      "examples": ["ex_v3_3_1", "ex_v3_3_2"]
    },
    {
      "id": "v3.4",
      "name": "向量垂直",
      "description": "垂直條件 $\\vec{a} \\perp \\vec{b} \\Leftrightarrow \\vec{a} \\cdot \\vec{b} = 0$",
      "category": "進階應用",
      "level": 3,
      "prerequisites": ["v3.1"],
      "related": [],
      "tags": ["垂直", "內積應用"],
      "examples": ["ex_v3_4_1", "ex_v3_4_2"]
    },
    {
      "id": "v3.5",
      "name": "正射影",
      "description": "純量投影 $\\frac{\\vec{a} \\cdot \\vec{b}}{|\\vec{b}|}$，向量投影，點到直線距離",
      "category": "進階應用",
      "level": 3,
      "prerequisites": ["v3.1"],
      "related": ["v3.4"],
      "tags": ["投影", "正射影"],
      "examples": ["ex_v3_5_1", "ex_v3_5_2"]
    },
    {
      "id": "v3.6",
      "name": "柯西不等式",
      "description": "$(\\vec{a} \\cdot \\vec{b})^2 \\leq |\\vec{a}|^2 |\\vec{b}|^2$，等號成立於平行",
      "category": "進階應用",
      "level": 3,
      "prerequisites": ["v3.1", "v1.3"],
      "related": [],
      "tags": ["不等式", "柯西不等式"],
      "examples": ["ex_v3_6_1"]
    },
    {
      "id": "v3.7",
      "name": "面積計算",
      "description": "用向量求平行四邊形與三角形面積",
      "category": "進階應用",
      "level": 3,
      "prerequisites": ["v3.1"],
      "related": [],
      "tags": ["面積", "幾何應用"],
      "examples": ["ex_v3_7_1", "ex_v3_7_2"]
    },
    {
      "id": "v3.8",
      "name": "三角形四心",
      "description": "重心、外心、內心、垂心的向量表示與歐拉線",
      "category": "進階應用",
      "level": 3,
      "prerequisites": ["v2.6", "v3.4"],
      "related": [],
      "tags": ["三角形", "四心", "歐拉線"],
      "examples": ["ex_v3_8_1", "ex_v3_8_2", "ex_v3_8_3"]
    },
    {
      "id": "v4.1",
      "name": "三維向量基礎",
      "description": "三維坐標系，空間向量 $(x, y, z)$，空間長度與距離",
      "category": "整合應用",
      "level": 4,
      "prerequisites": ["v1.3"],
      "related": [],
      "tags": ["三維空間", "空間向量"],
      "examples": ["ex_v4_1_1", "ex_v4_1_2"]
    },
    {
      "id": "v4.2",
      "name": "三維向量運算",
      "description": "三維加減法、純量積、內積 $x_1x_2 + y_1y_2 + z_1z_2$",
      "category": "整合應用",
      "level": 4,
      "prerequisites": ["v4.1", "v3.1"],
      "related": [],
      "tags": ["三維空間", "內積"],
      "examples": ["ex_v4_2_1", "ex_v4_2_2"]
    },
    {
      "id": "v4.3",
      "name": "向量外積",
      "description": "外積定義 $\\vec{a} \\times \\vec{b}$ 垂直於兩向量，大小 $|\\vec{a}||\\vec{b}|\\sin\\theta$",
      "category": "整合應用",
      "level": 4,
      "prerequisites": ["v4.1", "v3.1"],
      "related": [],
      "tags": ["外積", "叉積"],
      "examples": ["ex_v4_3_1", "ex_v4_3_2"]
    },
    {
      "id": "v4.4",
      "name": "外積的性質",
      "description": "反交換律、分配律、右手定則",
      "category": "整合應用",
      "level": 4,
      "prerequisites": ["v4.3"],
      "related": [],
      "tags": ["外積", "運算性質"],
      "examples": ["ex_v4_4_1"]
    },
    {
      "id": "v4.5",
      "name": "外積的應用",
      "description": "平行四邊形面積、三角形面積、判定平行共面、求法向量",
      "category": "整合應用",
      "level": 4,
      "prerequisites": ["v4.3"],
      "related": [],
      "tags": ["外積應用", "面積", "法向量"],
      "examples": ["ex_v4_5_1", "ex_v4_5_2"]
    },
    {
      "id": "v4.6",
      "name": "空間平面方程式",
      "description": "法向量與平面方程式，點法式、一般式 $Ax + By + Cz = D$",
      "category": "整合應用",
      "level": 4,
      "prerequisites": ["v4.3", "v3.4"],
      "related": [],
      "tags": ["平面方程式", "法向量"],
      "examples": ["ex_v4_6_1", "ex_v4_6_2"]
    },
    {
      "id": "v4.7",
      "name": "空間直線方程式",
      "description": "參數式 $\\vec{r} = \\vec{r_0} + t\\vec{v}$，對稱式，兩點式",
      "category": "整合應用",
      "level": 4,
      "prerequisites": ["v4.1", "v2.3"],
      "related": [],
      "tags": ["直線方程式", "參數式"],
      "examples": ["ex_v4_7_1"]
    },
    {
      "id": "v4.8",
      "name": "點線面關係",
      "description": "點到平面距離、點到直線距離、兩直線夾角距離、直線與平面夾角",
      "category": "整合應用",
      "level": 4,
      "prerequisites": ["v4.6", "v4.7"],
      "related": ["v3.5"],
      "tags": ["空間幾何", "距離", "夾角"],
      "examples": ["ex_v4_8_1", "ex_v4_8_2"]
    },
    {
      "id": "v4.9",
      "name": "三重積",
      "description": "純量三重積 $\\vec{a} \\cdot (\\vec{b} \\times \\vec{c})$，體積應用，共面判定",
      "category": "整合應用",
      "level": 4,
      "prerequisites": ["v4.3", "v3.1"],
      "related": [],
      "tags": ["三重積", "體積"],
      "examples": ["ex_v4_9_1"]
    },
    {
      "id": "v5.1",
      "name": "電腦圖學應用",
      "description": "2D/3D 座標轉換、旋轉矩陣、向量在遊戲開發中的應用",
      "category": "資訊科學應用",
      "level": 5,
      "prerequisites": ["v2.3", "v3.1"],
      "related": ["v4.3"],
      "tags": ["電腦圖學", "遊戲開發", "座標轉換"],
      "examples": ["ex_v5_1_1", "ex_v5_1_2"]
    },
    {
      "id": "v5.2",
      "name": "機器學習應用",
      "description": "特徵向量、向量空間、餘弦相似度、詞向量表示",
      "category": "資訊科學應用",
      "level": 5,
      "prerequisites": ["v3.1", "v3.3"],
      "related": ["v2.4"],
      "tags": ["機器學習", "資料科學", "AI"],
      "examples": ["ex_v5_2_1", "ex_v5_2_2"]
    },
    {
      "id": "v5.3",
      "name": "影像處理",
      "description": "像素向量、濾波器（卷積）、邊緣偵測",
      "category": "資訊科學應用",
      "level": 5,
      "prerequisites": ["v3.1"],
      "related": [],
      "tags": ["影像處理", "電腦視覺"],
      "examples": ["ex_v5_3_1"]
    },
    {
      "id": "v5.4",
      "name": "導航與GPS",
      "description": "位置向量、位移計算、最短路徑、方位角",
      "category": "資訊科學應用",
      "level": 5,
      "prerequisites": ["v1.3", "v2.1"],
      "related": ["v3.3"],
      "tags": ["GPS", "導航", "地理資訊"],
      "examples": ["ex_v5_4_1"]
    },
    {
      "id": "v5.5",
      "name": "機器人學應用",
      "description": "機器人位置控制、路徑規劃、座標轉換、逆運動學",
      "category": "資訊科學應用",
      "level": 5,
      "prerequisites": ["v2.1", "v3.1", "v5.1"],
      "related": ["v4.1"],
      "tags": ["機器人", "路徑規劃", "控制"],
      "examples": ["ex_v5_5_1", "ex_v5_5_2"]
    },
    {
      "id": "v6.1",
      "name": "力與運動",
      "description": "力向量合成與分解、牛頓第二定律 $\\vec{F} = m\\vec{a}$",
      "category": "物理應用",
      "level": 6,
      "prerequisites": ["v2.1", "v2.2"],
      "related": [],
      "tags": ["力學", "牛頓定律"],
      "examples": ["ex_v6_1_1", "ex_v6_1_2"]
    },
    {
      "id": "v6.2",
      "name": "速度與加速度",
      "description": "速度向量、相對速度、加速度向量、拋體運動",
      "category": "物理應用",
      "level": 6,
      "prerequisites": ["v2.1"],
      "related": ["v1.3"],
      "tags": ["運動學", "拋體運動"],
      "examples": ["ex_v6_2_1", "ex_v6_2_2"]
    },
    {
      "id": "v6.3",
      "name": "功與能量",
      "description": "功的定義 $W = \\vec{F} \\cdot \\vec{d}$，內積的物理意義",
      "category": "物理應用",
      "level": 6,
      "prerequisites": ["v3.1"],
      "related": [],
      "tags": ["功", "能量", "內積應用"],
      "examples": ["ex_v6_3_1"]
    },
    {
      "id": "v6.4",
      "name": "力矩與角動量",
      "description": "力矩 $\\vec{\\tau} = \\vec{r} \\times \\vec{F}$，外積的物理意義、右手定則",
      "category": "物理應用",
      "level": 6,
      "prerequisites": ["v4.3"],
      "related": [],
      "tags": ["力矩", "角動量", "外積應用"],
      "examples": ["ex_v6_4_1"]
    },
    {
      "id": "v6.5",
      "name": "電磁學應用",
      "description": "電場向量、磁場向量、勞倫茲力 $\\vec{F} = q\\vec{v} \\times \\vec{B}$",
      "category": "物理應用",
      "level": 6,
      "prerequisites": ["v4.3"],
      "related": [],
      "tags": ["電磁學", "勞倫茲力"],
      "examples": ["ex_v6_5_1"]
    },
    {
      "id": "v7.1",
      "name": "經濟學應用",
      "description": "資源向量、線性規劃、生產可能曲線、供需平衡",
      "category": "跨領域應用",
      "level": 7,
      "prerequisites": ["v2.1", "v2.4"],
      "related": [],
      "tags": ["經濟學", "線性規劃", "資源分配"],
      "examples": ["ex_v7_1_1", "ex_v7_1_2"]
    },
    {
      "id": "v7.2",
      "name": "生物學應用",
      "description": "族群向量、生態系統模型、捕食者-獵物模型、族群動態",
      "category": "跨領域應用",
      "level": 7,
      "prerequisites": ["v2.1", "v4.10"],
      "related": [],
      "tags": ["生物學", "生態學", "族群模型"],
      "examples": ["ex_v7_2_1"]
    },
    {
      "id": "v7.3",
      "name": "網路分析",
      "description": "圖論與向量、鄰接矩陣、PageRank 算法、社群網路分析",
      "category": "跨領域應用",
      "level": 7,
      "prerequisites": ["v2.4", "v3.1"],
      "related": ["v5.2"],
      "tags": ["圖論", "網路科學", "PageRank"],
      "examples": ["ex_v7_3_1"]
    },
    {
      "id": "v7.4",
      "name": "密碼學應用",
      "description": "向量加密、Hill 密碼、線性密碼系統、模運算與向量",
      "category": "跨領域應用",
      "level": 7,
      "prerequisites": ["v2.3", "v2.4"],
      "related": [],
      "tags": ["密碼學", "加密", "資訊安全"],
      "examples": ["ex_v7_4_1"]
    }
  ],
  "examples": [
    {
      "id": "ex_v1_1_1",
      "title": "辨別向量與純量",
      "question": "下列何者為向量？\n(A) 溫度 30°C  (B) 位移 5 公尺向東  (C) 質量 10 kg  (D) 速度 60 km/h 向北",
      "answer": "(B)(D)",
      "solution": "向量必須同時具有大小和方向。\n(A) 溫度只有大小，無方向 → 純量\n(B) 位移有大小和方向 → 向量 ✓\n(C) 質量只有大小，無方向 → 純量\n(D) 速度有大小和方向 → 向量 ✓",
      "difficulty": "easy",
      "type": "choice",
      "relatedNodes": ["v1.1"],
      "tags": ["觀念理解", "向量定義"]
    },
    {
      "id": "ex_v1_1_2",
      "title": "向量相等",
      "question": "$\\vec{AB}$ 與 $\\vec{CD}$ 相等的充要條件為何？",
      "answer": "大小相等且方向相同",
      "solution": "兩向量相等須滿足：\n1. 長度相等：$|\\vec{AB}| = |\\vec{CD}|$\n2. 方向相同（平行且同向）\n\n注意：起點位置不影響向量相等（可平移）",
      "difficulty": "easy",
      "type": "calc",
      "relatedNodes": ["v1.1"],
      "tags": ["觀念理解"]
    },
    {
      "id": "ex_v1_2_1",
      "title": "坐標表示",
      "question": "已知 $A(1, 2)$，$B(4, 6)$，求 $\\vec{AB}$ 的坐標表示。",
      "answer": "$(3, 4)$",
      "solution": "$\\vec{AB}$ 的坐標 = 終點坐標 - 起點坐標\n\n$\\vec{AB} = (x_B - x_A, y_B - y_A)$\n$= (4 - 1, 6 - 2)$\n$= (3, 4)$",
      "difficulty": "easy",
      "type": "calc",
      "relatedNodes": ["v1.2"],
      "tags": ["坐標運算"]
    },
    {
      "id": "ex_v1_2_2",
      "title": "基底向量表示",
      "question": "將向量 $\\vec{a} = (3, -2)$ 用基底向量 $\\hat{i}, \\hat{j}$ 表示。",
      "answer": "$3\\hat{i} - 2\\hat{j}$",
      "solution": "基底向量：$\\hat{i} = (1, 0)$，$\\hat{j} = (0, 1)$\n\n$\\vec{a} = (3, -2)$\n$= 3(1, 0) + (-2)(0, 1)$\n$= 3\\hat{i} - 2\\hat{j}$",
      "difficulty": "easy",
      "type": "calc",
      "relatedNodes": ["v1.2"],
      "tags": ["基底向量"]
    },
    {
      "id": "ex_v1_3_1",
      "title": "計算向量長度",
      "question": "求 $\\vec{a} = (3, 4)$ 的長度。",
      "answer": "$5$",
      "solution": "向量長度公式：$|\\vec{a}| = \\sqrt{x^2 + y^2}$\n\n$|\\vec{a}| = \\sqrt{3^2 + 4^2}$\n$= \\sqrt{9 + 16}$\n$= \\sqrt{25}$\n$= 5$",
      "difficulty": "easy",
      "type": "calc",
      "relatedNodes": ["v1.3"],
      "tags": ["長度計算"]
    },
    {
      "id": "ex_v1_3_2",
      "title": "兩點距離",
      "question": "求點 $A(1, 2)$ 到 $B(4, 6)$ 的距離。",
      "answer": "$5$",
      "solution": "距離 = $|\\vec{AB}|$\n\n先求 $\\vec{AB} = (4-1, 6-2) = (3, 4)$\n\n$|\\vec{AB}| = \\sqrt{3^2 + 4^2} = \\sqrt{25} = 5$",
      "difficulty": "easy",
      "type": "calc",
      "relatedNodes": ["v1.3"],
      "tags": ["距離公式"]
    },
    {
      "id": "ex_v1_3_3",
      "title": "求未知坐標",
      "question": "已知 $\\vec{a} = (x, 6)$ 且 $|\\vec{a}| = 10$，求 $x$。",
      "answer": "$x = \\pm 8$",
      "solution": "$|\\vec{a}| = \\sqrt{x^2 + 6^2} = 10$\n\n平方：$x^2 + 36 = 100$\n$x^2 = 64$\n$x = \\pm 8$",
      "difficulty": "medium",
      "type": "calc",
      "relatedNodes": ["v1.3"],
      "tags": ["方程式"]
    },
    {
      "id": "ex_v1_4_1",
      "title": "單位向量",
      "question": "求與 $\\vec{a} = (3, 4)$ 同方向的單位向量。",
      "answer": "$(\\frac{3}{5}, \\frac{4}{5})$",
      "solution": "單位向量 $\\hat{a} = \\frac{\\vec{a}}{|\\vec{a}|}$\n\n先求長度：$|\\vec{a}| = \\sqrt{9 + 16} = 5$\n\n$\\hat{a} = \\frac{1}{5}(3, 4) = (\\frac{3}{5}, \\frac{4}{5})$\n\n驗證：$|(\\frac{3}{5}, \\frac{4}{5})| = \\sqrt{\\frac{9}{25} + \\frac{16}{25}} = 1$ ✓",
      "difficulty": "medium",
      "type": "calc",
      "relatedNodes": ["v1.4"],
      "tags": ["單位化"]
    },
    {
      "id": "ex_v1_4_2",
      "title": "零向量性質",
      "question": "下列關於零向量 $\\vec{0}$ 的敘述何者正確？\n(A) $|\\vec{0}| = 0$  (B) $\\vec{0}$ 沒有方向  (C) $\\vec{a} + \\vec{0} = \\vec{a}$  (D) 以上皆是",
      "answer": "(D)",
      "solution": "零向量的性質：\n(A) 長度為 0：$|\\vec{0}| = 0$ ✓\n(B) 方向不確定（或說任意方向）✓\n(C) 加法單位元素：$\\vec{a} + \\vec{0} = \\vec{a}$ ✓\n\n答案：(D) 以上皆是",
      "difficulty": "easy",
      "type": "choice",
      "relatedNodes": ["v1.4"],
      "tags": ["觀念理解"]
    },
    {
      "id": "ex_v2_1_1",
      "title": "向量加法基礎",
      "question": "計算 $(2, 3) + (1, -5)$",
      "answer": "$(3, -2)$",
      "solution": "向量加法：對應分量相加\n\n$(2, 3) + (1, -5)$\n$= (2+1, 3+(-5))$\n$= (3, -2)$",
      "difficulty": "easy",
      "type": "calc",
      "relatedNodes": ["v2.1"],
      "tags": ["基本運算"]
    },
    {
      "id": "ex_v2_1_2",
      "title": "三角形法則",
      "question": "已知 $\\vec{AB} = (2, 1)$，$\\vec{BC} = (3, 4)$，求 $\\vec{AC}$。",
      "answer": "$(5, 5)$",
      "solution": "三角形法則：$\\vec{AC} = \\vec{AB} + \\vec{BC}$\n\n$\\vec{AC} = (2, 1) + (3, 4)$\n$= (5, 5)$",
      "difficulty": "easy",
      "type": "calc",
      "relatedNodes": ["v2.1"],
      "tags": ["幾何應用"]
    },
    {
      "id": "ex_v2_1_3",
      "title": "平行四邊形法則",
      "question": "平行四邊形 $ABCD$，若 $\\vec{AB} = \\vec{a}$，$\\vec{AD} = \\vec{b}$，求對角線 $\\vec{AC}$。",
      "answer": "$\\vec{a} + \\vec{b}$",
      "solution": "平行四邊形法則：對角線為兩鄰邊向量和\n\n$\\vec{AC} = \\vec{AB} + \\vec{BC}$\n$= \\vec{AB} + \\vec{AD}$（因為 $\\vec{BC} = \\vec{AD}$）\n$= \\vec{a} + \\vec{b}$",
      "difficulty": "medium",
      "type": "calc",
      "relatedNodes": ["v2.1"],
      "tags": ["平行四邊形"]
    },
    {
      "id": "ex_v2_2_1",
      "title": "向量減法",
      "question": "計算 $(5, 7) - (2, 3)$",
      "answer": "$(3, 4)$",
      "solution": "向量減法：對應分量相減\n\n$(5, 7) - (2, 3)$\n$= (5-2, 7-3)$\n$= (3, 4)$",
      "difficulty": "easy",
      "type": "calc",
      "relatedNodes": ["v2.2"],
      "tags": ["基本運算"]
    },
    {
      "id": "ex_v2_2_2",
      "title": "幾何意義",
      "question": "已知 $A(1, 2)$，$B(5, 7)$，用向量減法求 $\\vec{AB}$。",
      "answer": "$(4, 5)$",
      "solution": "$\\vec{AB} = \\vec{OB} - \\vec{OA}$\n\n$= (5, 7) - (1, 2)$\n$= (4, 5)$",
      "difficulty": "easy",
      "type": "calc",
      "relatedNodes": ["v2.2"],
      "tags": ["幾何應用"]
    },
    {
      "id": "ex_v2_3_1",
      "title": "純量積計算",
      "question": "計算 $3(2, -1)$",
      "answer": "$(6, -3)$",
      "solution": "純量積：每個分量都乘以純量\n\n$3(2, -1)$\n$= (3 \\times 2, 3 \\times (-1))$\n$= (6, -3)$",
      "difficulty": "easy",
      "type": "calc",
      "relatedNodes": ["v2.3"],
      "tags": ["基本運算"]
    },
    {
      "id": "ex_v2_3_2",
      "title": "反向向量",
      "question": "求與 $\\vec{a} = (4, 3)$ 反向且長度為 10 的向量。",
      "answer": "$(-8, -6)$",
      "solution": "先求 $\\vec{a}$ 的長度：$|\\vec{a}| = \\sqrt{16 + 9} = 5$\n\n反向向量：$-\\vec{a} = (-4, -3)$\n長度變為 10（原長度的 2 倍）\n\n所求 $= -2\\vec{a} = (-8, -6)$\n\n驗證：$|(-8, -6)| = \\sqrt{64 + 36} = 10$ ✓",
      "difficulty": "medium",
      "type": "calc",
      "relatedNodes": ["v2.3"],
      "tags": ["向量縮放"]
    },
    {
      "id": "ex_v2_4_1",
      "title": "線性組合",
      "question": "若 $\\vec{c} = 2\\vec{a} - 3\\vec{b}$，且 $\\vec{a} = (1, 2)$，$\\vec{b} = (3, -1)$，求 $\\vec{c}$。",
      "answer": "$(-7, 7)$",
      "solution": "$\\vec{c} = 2\\vec{a} - 3\\vec{b}$\n$= 2(1, 2) - 3(3, -1)$\n$= (2, 4) - (9, -3)$\n$= (2-9, 4-(-3))$\n$= (-7, 7)$",
      "difficulty": "medium",
      "type": "calc",
      "relatedNodes": ["v2.4"],
      "tags": ["線性組合"]
    },
    {
      "id": "ex_v2_5_1",
      "title": "判定平行",
      "question": "$\\vec{a} = (2, 3)$ 與 $\\vec{b} = (4, 6)$ 是否平行？",
      "answer": "是",
      "solution": "平行條件：$\\vec{b} = k\\vec{a}$\n\n$\\vec{b} = (4, 6) = 2(2, 3) = 2\\vec{a}$\n\n因為存在 $k = 2$ 使得 $\\vec{b} = k\\vec{a}$，故平行 ✓",
      "difficulty": "easy",
      "type": "calc",
      "relatedNodes": ["v2.5"],
      "tags": ["平行判定"]
    },
    {
      "id": "ex_v2_5_2",
      "title": "三點共線",
      "question": "判斷 $A(1, 2)$，$B(3, 5)$，$C(5, 8)$ 是否共線。",
      "answer": "是",
      "solution": "三點共線 ⟺ $\\vec{AB} \\parallel \\vec{AC}$\n\n$\\vec{AB} = (2, 3)$\n$\\vec{AC} = (4, 6) = 2(2, 3) = 2\\vec{AB}$\n\n因為 $\\vec{AC} = 2\\vec{AB}$，故 $A, B, C$ 共線 ✓",
      "difficulty": "medium",
      "type": "calc",
      "relatedNodes": ["v2.5"],
      "tags": ["共線"]
    },
    {
      "id": "ex_v2_6_1",
      "title": "中點公式",
      "question": "求 $A(1, 2)$ 和 $B(5, 8)$ 的中點 $M$ 的坐標。",
      "answer": "$(3, 5)$",
      "solution": "中點公式：$\\vec{OM} = \\frac{\\vec{OA} + \\vec{OB}}{2}$\n\n$\\vec{OM} = \\frac{(1, 2) + (5, 8)}{2}$\n$= \\frac{(6, 10)}{2}$\n$= (3, 5)$",
      "difficulty": "easy",
      "type": "calc",
      "relatedNodes": ["v2.6"],
      "tags": ["中點"]
    },
    {
      "id": "ex_v2_6_2",
      "title": "內分點",
      "question": "點 $P$ 分 $\\overline{AB}$ 為 $2:3$（靠近 $A$），若 $A(1, 2)$，$B(6, 12)$，求 $P$ 坐標。",
      "answer": "$(3, 6)$",
      "solution": "內分點公式：$\\vec{OP} = \\frac{n\\vec{OA} + m\\vec{OB}}{m+n}$\n\n$m:n = 2:3$，所以 $m=2, n=3$\n\n$\\vec{OP} = \\frac{3(1, 2) + 2(6, 12)}{2+3}$\n$= \\frac{(3, 6) + (12, 24)}{5}$\n$= \\frac{(15, 30)}{5}$\n$= (3, 6)$",
      "difficulty": "medium",
      "type": "calc",
      "relatedNodes": ["v2.6"],
      "tags": ["分點", "比例"]
    },
    {
      "id": "ex_v2_6_3",
      "title": "三角形重心",
      "question": "三角形 $ABC$ 的頂點為 $A(0, 0)$，$B(6, 0)$，$C(0, 6)$，求重心 $G$ 坐標。",
      "answer": "$(2, 2)$",
      "solution": "重心公式：$\\vec{OG} = \\frac{\\vec{OA} + \\vec{OB} + \\vec{OC}}{3}$\n\n$\\vec{OG} = \\frac{(0, 0) + (6, 0) + (0, 6)}{3}$\n$= \\frac{(6, 6)}{3}$\n$= (2, 2)$",
      "difficulty": "easy",
      "type": "calc",
      "relatedNodes": ["v2.6"],
      "tags": ["重心"]
    },
    {
      "id": "ex_v2_7_1",
      "title": "直線向量方程式",
      "question": "過點 $(1, 2)$ 且方向向量為 $(3, 4)$ 的直線向量方程式為何？",
      "answer": "$(x, y) = (1, 2) + t(3, 4)$",
      "solution": "直線向量方程式：$\\vec{r} = \\vec{r_0} + t\\vec{v}$\n\n過點 $(1, 2)$，方向向量 $(3, 4)$\n\n$(x, y) = (1, 2) + t(3, 4)$\n\n展開：$x = 1 + 3t$，$y = 2 + 4t$",
      "difficulty": "easy",
      "type": "calc",
      "relatedNodes": ["v2.7"],
      "tags": ["直線方程式"]
    },
    {
      "id": "ex_v2_7_2",
      "title": "兩點決定直線",
      "question": "求通過 $A(1, 1)$ 和 $B(4, 5)$ 的直線向量方程式。",
      "answer": "$(x, y) = (1, 1) + t(3, 4)$",
      "solution": "方向向量：$\\vec{AB} = (4-1, 5-1) = (3, 4)$\n\n直線方程式：\n$(x, y) = (1, 1) + t(3, 4)$\n\n或：$(x, y) = (4, 5) + s(-3, -4)$（用點 B）",
      "difficulty": "medium",
      "type": "calc",
      "relatedNodes": ["v2.7"],
      "tags": ["直線方程式"]
    },
    {
      "id": "ex_v2_8_1",
      "title": "三角不等式",
      "question": "證明 $|\\vec{a} + \\vec{b}| \\leq |\\vec{a}| + |\\vec{b}|$",
      "answer": "見詳解",
      "solution": "幾何意義：三角形兩邊之和大於第三邊\n\n證明：\n$|\\vec{a} + \\vec{b}|^2 = (\\vec{a} + \\vec{b}) \\cdot (\\vec{a} + \\vec{b})$\n$= |\\vec{a}|^2 + 2\\vec{a} \\cdot \\vec{b} + |\\vec{b}|^2$\n$\\leq |\\vec{a}|^2 + 2|\\vec{a}||\\vec{b}| + |\\vec{b}|^2$（柯西不等式）\n$= (|\\vec{a}| + |\\vec{b}|)^2$\n\n等號成立：$\\vec{a}$ 與 $\\vec{b}$ 同向",
      "difficulty": "hard",
      "type": "proof",
      "relatedNodes": ["v2.8"],
      "tags": ["不等式", "證明"]
    },
    {
      "id": "ex_v2_8_2",
      "title": "反向三角不等式",
      "question": "已知 $|\\vec{a}| = 5$，$|\\vec{b}| = 3$，求 $|\\vec{a} - \\vec{b}|$ 的範圍。",
      "answer": "$2 \\leq |\\vec{a} - \\vec{b}| \\leq 8$",
      "solution": "反向三角不等式：\n$||\\vec{a}| - |\\vec{b}|| \\leq |\\vec{a} - \\vec{b}| \\leq |\\vec{a}| + |\\vec{b}|$\n\n$|5 - 3| \\leq |\\vec{a} - \\vec{b}| \\leq 5 + 3$\n$2 \\leq |\\vec{a} - \\vec{b}| \\leq 8$\n\n下界：同向時；上界：反向時",
      "difficulty": "medium",
      "type": "calc",
      "relatedNodes": ["v2.8"],
      "tags": ["不等式"]
    },
    {
      "id": "ex_v3_9_1",
      "title": "複數與向量對應",
      "question": "複數 $z = 3 + 4i$ 對應的向量為何？求其長度。",
      "answer": "$(3, 4)$，長度 $5$",
      "solution": "複數 $z = a + bi$ 對應向量 $(a, b)$\n\n$z = 3 + 4i$ → 向量 $(3, 4)$\n\n長度（模）：$|z| = \\sqrt{3^2 + 4^2} = 5$",
      "difficulty": "easy",
      "type": "calc",
      "relatedNodes": ["v3.9"],
      "tags": ["複數"]
    },
    {
      "id": "ex_v3_9_2",
      "title": "複數乘法與旋轉",
      "question": "複數 $z = 1 + i$ 乘以 $i$ 後，向量如何變化？",
      "answer": "逆時針旋轉 $90°$",
      "solution": "$z = 1 + i$ → 向量 $(1, 1)$\n\n$zi = (1 + i) \\cdot i = i + i^2 = -1 + i$\n→ 向量 $(-1, 1)$\n\n結論：乘以 $i$ 相當於向量逆時針旋轉 $90°$",
      "difficulty": "medium",
      "type": "calc",
      "relatedNodes": ["v3.9"],
      "tags": ["複數", "旋轉"]
    },
    {
      "id": "ex_v3_10_1",
      "title": "極坐標轉換",
      "question": "將極坐標 $(r, \\theta) = (5, 60°)$ 轉換為直角坐標。",
      "answer": "$(\\frac{5}{2}, \\frac{5\\sqrt{3}}{2})$",
      "solution": "轉換公式：\n$x = r\\cos\\theta$，$y = r\\sin\\theta$\n\n$x = 5\\cos 60° = 5 \\times \\frac{1}{2} = \\frac{5}{2}$\n$y = 5\\sin 60° = 5 \\times \\frac{\\sqrt{3}}{2} = \\frac{5\\sqrt{3}}{2}$",
      "difficulty": "easy",
      "type": "calc",
      "relatedNodes": ["v3.10"],
      "tags": ["極坐標", "轉換"]
    },
    {
      "id": "ex_v3_10_2",
      "title": "直角轉極坐標",
      "question": "將直角坐標 $(3, 3)$ 轉換為極坐標。",
      "answer": "$(3\\sqrt{2}, 45°)$",
      "solution": "$r = \\sqrt{x^2 + y^2} = \\sqrt{9 + 9} = 3\\sqrt{2}$\n\n$\\tan\\theta = \\frac{y}{x} = \\frac{3}{3} = 1$\n$\\theta = 45°$\n\n極坐標：$(3\\sqrt{2}, 45°)$",
      "difficulty": "easy",
      "type": "calc",
      "relatedNodes": ["v3.10"],
      "tags": ["極坐標", "轉換"]
    },
    {
      "id": "ex_v4_10_1",
      "title": "速度向量（微積分）",
      "question": "質點位置 $\\vec{r}(t) = (t^2, 2t)$，求 $t=1$ 時的速度向量。",
      "answer": "$(2, 2)$",
      "solution": "速度向量：$\\vec{v}(t) = \\frac{d\\vec{r}}{dt}$\n\n$\\vec{v}(t) = (\\frac{d(t^2)}{dt}, \\frac{d(2t)}{dt}) = (2t, 2)$\n\n$t=1$ 時：$\\vec{v}(1) = (2, 2)$",
      "difficulty": "medium",
      "type": "calc",
      "relatedNodes": ["v4.10"],
      "tags": ["微積分", "速度"]
    },
    {
      "id": "ex_v4_10_2",
      "title": "加速度向量",
      "question": "承上題，求 $t=1$ 時的加速度向量。",
      "answer": "$(2, 0)$",
      "solution": "加速度向量：$\\vec{a}(t) = \\frac{d\\vec{v}}{dt} = \\frac{d^2\\vec{r}}{dt^2}$\n\n$\\vec{a}(t) = (\\frac{d(2t)}{dt}, \\frac{d(2)}{dt}) = (2, 0)$\n\n$t=1$ 時：$\\vec{a}(1) = (2, 0)$",
      "difficulty": "medium",
      "type": "calc",
      "relatedNodes": ["v4.10"],
      "tags": ["微積分", "加速度"]
    },
    {
      "id": "ex_v5_5_1",
      "title": "機器人路徑規劃",
      "question": "機器人從 $(0, 0)$ 移動到 $(6, 8)$，速度 $2$ m/s，需要多少時間？",
      "answer": "$5$ 秒",
      "solution": "位移向量：$\\vec{d} = (6, 8) - (0, 0) = (6, 8)$\n\n距離：$|\\vec{d}| = \\sqrt{36 + 64} = 10$ m\n\n時間：$t = \\frac{\\text{距離}}{\\text{速度}} = \\frac{10}{2} = 5$ 秒",
      "difficulty": "easy",
      "type": "calc",
      "relatedNodes": ["v5.5"],
      "tags": ["機器人", "路徑規劃"]
    },
    {
      "id": "ex_v5_5_2",
      "title": "機器手臂位置",
      "question": "機器手臂兩節，第一節長 $3$ m 角度 $30°$，第二節長 $2$ m 角度 $60°$，求末端位置。",
      "answer": "約 $(2.6, 3.2)$",
      "solution": "第一節末端：\n$(3\\cos 30°, 3\\sin 30°) = (\\frac{3\\sqrt{3}}{2}, \\frac{3}{2})$\n\n第二節相對向量：\n$(2\\cos 60°, 2\\sin 60°) = (1, \\sqrt{3})$\n\n末端位置：\n$(\\frac{3\\sqrt{3}}{2} + 1, \\frac{3}{2} + \\sqrt{3}) \\approx (2.6, 3.2)$",
      "difficulty": "hard",
      "type": "calc",
      "relatedNodes": ["v5.5"],
      "tags": ["機器人", "逆運動學"]
    },
    {
      "id": "ex_v7_1_1",
      "title": "資源分配",
      "question": "工廠生產 A、B 兩產品，資源向量 $(勞力, 原料) = (100, 80)$，A 需 $(2, 3)$，B 需 $(3, 2)$，如何分配？",
      "answer": "多種方案，如 $20A + 20B$",
      "solution": "設生產 $x$ 個 A，$y$ 個 B\n\n限制條件：\n$2x + 3y \\leq 100$（勞力）\n$3x + 2y \\leq 80$（原料）\n$x, y \\geq 0$\n\n一組可行解：$x = 20, y = 20$\n檢驗：$2(20) + 3(20) = 100$ ✓\n$3(20) + 2(20) = 100 > 80$ ✗\n\n需用線性規劃求最優解",
      "difficulty": "hard",
      "type": "calc",
      "relatedNodes": ["v7.1"],
      "tags": ["線性規劃", "經濟"]
    },
    {
      "id": "ex_v7_1_2",
      "title": "供需平衡",
      "question": "市場供給向量 $(100, 150)$（兩種商品），需求 $(120, 130)$，如何調整？",
      "answer": "商品 1 不足，商品 2 過剩",
      "solution": "差額向量：\n需求 - 供給 $= (120, 130) - (100, 150) = (20, -20)$\n\n商品 1：需求 > 供給，不足 $20$ 單位（漲價）\n商品 2：需求 < 供給，過剩 $20$ 單位（降價）",
      "difficulty": "medium",
      "type": "calc",
      "relatedNodes": ["v7.1"],
      "tags": ["供需", "經濟"]
    },
    {
      "id": "ex_v7_2_1",
      "title": "族群模型",
      "question": "兔子與狐狸族群向量 $(R, F) = (100, 20)$，一年後 $(80, 30)$，分析變化。",
      "answer": "兔子減少，狐狸增加",
      "solution": "變化向量：\n$(80, 30) - (100, 20) = (-20, 10)$\n\n分析：\n- 兔子減少 $20$ 隻（被捕食）\n- 狐狸增加 $10$ 隻（食物充足）\n\n捕食者-獵物模型：族群數量呈週期性震盪",
      "difficulty": "medium",
      "type": "calc",
      "relatedNodes": ["v7.2"],
      "tags": ["生態學", "族群"]
    },
    {
      "id": "ex_v7_3_1",
      "title": "PageRank 簡化",
      "question": "網頁 A 連結到 B、C，用向量表示連結關係。",
      "answer": "鄰接向量",
      "solution": "鄰接向量表示：\nA 指向 B, C：$(0, 1, 1)$\n\nPageRank 概念：\n網頁重要性 = 指向它的網頁重要性之和\n用向量迭代計算收斂值\n\n實際算法更複雜（阻尼係數、歸一化）",
      "difficulty": "hard",
      "type": "calc",
      "relatedNodes": ["v7.3"],
      "tags": ["網路", "PageRank"]
    },
    {
      "id": "ex_v7_4_1",
      "title": "Hill 密碼",
      "question": "用矩陣 $\\begin{pmatrix} 2 & 3 \\\\ 1 & 2 \\end{pmatrix}$ 加密訊息向量 $(1, 2)$（mod 26）。",
      "answer": "$(8, 5)$",
      "solution": "加密：$\\vec{c} = A\\vec{m} \\pmod{26}$\n\n$\\begin{pmatrix} 2 & 3 \\\\ 1 & 2 \\end{pmatrix} \\begin{pmatrix} 1 \\\\ 2 \\end{pmatrix} = \\begin{pmatrix} 2+6 \\\\ 1+4 \\end{pmatrix} = \\begin{pmatrix} 8 \\\\ 5 \\end{pmatrix}$\n\n密文向量：$(8, 5)$ 對應字母 I, F",
      "difficulty": "hard",
      "type": "calc",
      "relatedNodes": ["v7.4"],
      "tags": ["密碼學", "加密"]
    },
    {
      "id": "ex_v3_1_1",
      "title": "內積計算",
      "question": "計算 $(3, 4) \\cdot (1, 2)$",
      "answer": "$11$",
      "solution": "內積公式：$\\vec{a} \\cdot \\vec{b} = x_1x_2 + y_1y_2$\n\n$(3, 4) \\cdot (1, 2)$\n$= 3 \\times 1 + 4 \\times 2$\n$= 3 + 8$\n$= 11$",
      "difficulty": "easy",
      "type": "calc",
      "relatedNodes": ["v3.1"],
      "tags": ["內積"]
    },
    {
      "id": "ex_v3_1_2",
      "title": "求夾角",
      "question": "求 $\\vec{a} = (1, 0)$ 與 $\\vec{b} = (1, 1)$ 的夾角。",
      "answer": "$45°$",
      "solution": "夾角公式：$\\cos\\theta = \\frac{\\vec{a} \\cdot \\vec{b}}{|\\vec{a}||\\vec{b}|}$\n\n內積：$\\vec{a} \\cdot \\vec{b} = 1 \\times 1 + 0 \\times 1 = 1$\n長度：$|\\vec{a}| = 1$，$|\\vec{b}| = \\sqrt{2}$\n\n$\\cos\\theta = \\frac{1}{1 \\times \\sqrt{2}} = \\frac{\\sqrt{2}}{2}$\n\n$\\theta = 45°$",
      "difficulty": "medium",
      "type": "calc",
      "relatedNodes": ["v3.1"],
      "tags": ["夾角", "三角函數"]
    },
    {
      "id": "ex_v3_1_3",
      "title": "內積應用",
      "question": "已知 $|\\vec{a}| = 3$，$|\\vec{b}| = 4$，$\\vec{a} \\cdot \\vec{b} = 6$，求兩向量夾角 $\\theta$。",
      "answer": "$60°$",
      "solution": "$\\cos\\theta = \\frac{\\vec{a} \\cdot \\vec{b}}{|\\vec{a}||\\vec{b}|}$\n\n$= \\frac{6}{3 \\times 4} = \\frac{1}{2}$\n\n$\\theta = 60°$",
      "difficulty": "medium",
      "type": "calc",
      "relatedNodes": ["v3.1"],
      "tags": ["夾角"]
    },
    {
      "id": "ex_v3_2_1",
      "title": "內積性質",
      "question": "已知 $|\\vec{a}| = 5$，求 $\\vec{a} \\cdot \\vec{a}$。",
      "answer": "$25$",
      "solution": "性質：$\\vec{a} \\cdot \\vec{a} = |\\vec{a}|^2$\n\n$\\vec{a} \\cdot \\vec{a} = 5^2 = 25$",
      "difficulty": "easy",
      "type": "calc",
      "relatedNodes": ["v3.2"],
      "tags": ["性質"]
    },
    {
      "id": "ex_v3_3_1",
      "title": "判斷銳鈍角",
      "question": "$\\vec{a} = (2, 1)$ 與 $\\vec{b} = (-1, 3)$ 的夾角為銳角、直角或鈍角？",
      "answer": "銳角",
      "solution": "判斷方法：看內積正負\n\n$\\vec{a} \\cdot \\vec{b} = 2 \\times (-1) + 1 \\times 3 = -2 + 3 = 1 > 0$\n\n內積 $> 0$ → 夾角為銳角",
      "difficulty": "easy",
      "type": "calc",
      "relatedNodes": ["v3.3"],
      "tags": ["夾角判定"]
    },
    {
      "id": "ex_v3_3_2",
      "title": "方向餘弦",
      "question": "求向量 $\\vec{a} = (1, \\sqrt{3})$ 與 $x$ 軸正向的夾角。",
      "answer": "$60°$",
      "solution": "$x$ 軸正向單位向量：$\\hat{i} = (1, 0)$\n\n$\\cos\\theta = \\frac{\\vec{a} \\cdot \\hat{i}}{|\\vec{a}|} = \\frac{1 \\times 1 + \\sqrt{3} \\times 0}{\\sqrt{1 + 3}} = \\frac{1}{2}$\n\n$\\theta = 60°$",
      "difficulty": "medium",
      "type": "calc",
      "relatedNodes": ["v3.3"],
      "tags": ["方向角"]
    },
    {
      "id": "ex_v3_4_1",
      "title": "垂直判定",
      "question": "$\\vec{a} = (2, 3)$ 與 $\\vec{b} = (3, -2)$ 是否垂直？",
      "answer": "是",
      "solution": "垂直條件：$\\vec{a} \\cdot \\vec{b} = 0$\n\n$\\vec{a} \\cdot \\vec{b} = 2 \\times 3 + 3 \\times (-2)$\n$= 6 - 6 = 0$\n\n內積為 0，故 $\\vec{a} \\perp \\vec{b}$ ✓",
      "difficulty": "easy",
      "type": "calc",
      "relatedNodes": ["v3.4"],
      "tags": ["垂直"]
    },
    {
      "id": "ex_v3_4_2",
      "title": "求垂直向量",
      "question": "求與 $\\vec{a} = (4, 3)$ 垂直的一個向量。",
      "answer": "$(3, -4)$ 或 $(-3, 4)$",
      "solution": "方法：坐標對調，一者變號\n\n設所求向量為 $(x, y)$\n垂直條件：$(x, y) \\cdot (4, 3) = 0$\n$4x + 3y = 0$\n\n一組解：$x = 3, y = -4$ → $(3, -4)$\n另一組解：$x = -3, y = 4$ → $(-3, 4)$",
      "difficulty": "medium",
      "type": "calc",
      "relatedNodes": ["v3.4"],
      "tags": ["垂直", "構造"]
    },
    {
      "id": "ex_v3_5_1",
      "title": "純量投影",
      "question": "$\\vec{a} = (3, 4)$ 在 $\\vec{b} = (1, 0)$ 上的正射影長度為何？",
      "answer": "$3$",
      "solution": "純量投影：$\\text{proj}_b a = \\frac{\\vec{a} \\cdot \\vec{b}}{|\\vec{b}|}$\n\n$\\vec{a} \\cdot \\vec{b} = 3 \\times 1 + 4 \\times 0 = 3$\n$|\\vec{b}| = 1$\n\n投影長度 $= \\frac{3}{1} = 3$",
      "difficulty": "easy",
      "type": "calc",
      "relatedNodes": ["v3.5"],
      "tags": ["投影"]
    },
    {
      "id": "ex_v3_5_2",
      "title": "向量投影",
      "question": "$\\vec{a} = (2, 3)$ 在 $\\vec{b} = (1, 1)$ 上的向量投影為何？",
      "answer": "$(\\frac{5}{2}, \\frac{5}{2})$",
      "solution": "向量投影：$\\text{proj}_b \\vec{a} = \\frac{\\vec{a} \\cdot \\vec{b}}{|\\vec{b}|^2} \\vec{b}$\n\n$\\vec{a} \\cdot \\vec{b} = 2 + 3 = 5$\n$|\\vec{b}|^2 = 1 + 1 = 2$\n\n$\\text{proj}_b \\vec{a} = \\frac{5}{2}(1, 1) = (\\frac{5}{2}, \\frac{5}{2})$",
      "difficulty": "medium",
      "type": "calc",
      "relatedNodes": ["v3.5"],
      "tags": ["投影", "向量形式"]
    },
    {
      "id": "ex_v3_6_1",
      "title": "柯西不等式",
      "question": "證明對任意實數 $x_1, y_1, x_2, y_2$，有 $(x_1x_2 + y_1y_2)^2 \\leq (x_1^2 + y_1^2)(x_2^2 + y_2^2)$。",
      "answer": "見詳解",
      "solution": "設 $\\vec{a} = (x_1, y_1)$，$\\vec{b} = (x_2, y_2)$\n\n由向量內積定義：\n$(\\vec{a} \\cdot \\vec{b})^2 \\leq |\\vec{a}|^2 |\\vec{b}|^2$\n\n即：$(x_1x_2 + y_1y_2)^2 \\leq (x_1^2 + y_1^2)(x_2^2 + y_2^2)$\n\n等號成立條件：$\\vec{a} \\parallel \\vec{b}$",
      "difficulty": "hard",
      "type": "proof",
      "relatedNodes": ["v3.6"],
      "tags": ["不等式", "證明"]
    },
    {
      "id": "ex_v3_7_1",
      "title": "三角形面積",
      "question": "求頂點為 $A(0, 0)$，$B(4, 0)$，$C(0, 3)$ 的三角形面積。",
      "answer": "$6$",
      "solution": "方法一：用向量\n$\\vec{AB} = (4, 0)$，$\\vec{AC} = (0, 3)$\n面積 $= \\frac{1}{2}|x_1y_2 - x_2y_1| = \\frac{1}{2}|4 \\times 3 - 0 \\times 0| = 6$\n\n方法二：直接計算\n面積 $= \\frac{1}{2} \\times 4 \\times 3 = 6$",
      "difficulty": "easy",
      "type": "calc",
      "relatedNodes": ["v3.7"],
      "tags": ["面積"]
    },
    {
      "id": "ex_v3_7_2",
      "title": "平行四邊形面積",
      "question": "平行四邊形兩鄰邊為 $\\vec{a} = (3, 1)$ 和 $\\vec{b} = (1, 2)$，求面積。",
      "answer": "$5$",
      "solution": "平行四邊形面積 $= |x_1y_2 - x_2y_1|$\n\n$= |3 \\times 2 - 1 \\times 1|$\n$= |6 - 1|$\n$= 5$",
      "difficulty": "easy",
      "type": "calc",
      "relatedNodes": ["v3.7"],
      "tags": ["面積"]
    },
    {
      "id": "ex_v3_8_1",
      "title": "三角形重心",
      "question": "三角形 $ABC$ 頂點為 $A(1, 1)$，$B(4, 1)$，$C(1, 5)$，求重心 $G$ 坐標。",
      "answer": "$(2, \\frac{7}{3})$",
      "solution": "重心公式：$G = \\frac{A + B + C}{3}$\n\n$G = \\frac{(1,1) + (4,1) + (1,5)}{3}$\n$= \\frac{(6, 7)}{3}$\n$= (2, \\frac{7}{3})$",
      "difficulty": "easy",
      "type": "calc",
      "relatedNodes": ["v3.8"],
      "tags": ["重心"]
    },
    {
      "id": "ex_v3_8_2",
      "title": "外心性質",
      "question": "說明三角形外心的向量性質。",
      "answer": "到三頂點等距",
      "solution": "設外心為 $O$，則：\n$|\\vec{OA}| = |\\vec{OB}| = |\\vec{OC}|$（外接圓半徑）\n\n等價於：\n$|\\vec{OA}|^2 = |\\vec{OB}|^2 = |\\vec{OC}|^2$\n\n可用此條件列方程求外心坐標",
      "difficulty": "medium",
      "type": "calc",
      "relatedNodes": ["v3.8"],
      "tags": ["外心"]
    },
    {
      "id": "ex_v3_8_3",
      "title": "垂心性質",
      "question": "說明三角形垂心的向量性質。",
      "answer": "三高交點",
      "solution": "設垂心為 $H$，則：\n$\\vec{AH} \\perp \\vec{BC}$ → $\\vec{AH} \\cdot \\vec{BC} = 0$\n$\\vec{BH} \\perp \\vec{AC}$ → $\\vec{BH} \\cdot \\vec{AC} = 0$\n$\\vec{CH} \\perp \\vec{AB}$ → $\\vec{CH} \\cdot \\vec{AB} = 0$\n\n可用垂直條件列方程求垂心坐標",
      "difficulty": "medium",
      "type": "calc",
      "relatedNodes": ["v3.8"],
      "tags": ["垂心"]
    },
    {
      "id": "ex_v4_1_1",
      "title": "三維向量長度",
      "question": "求 $\\vec{a} = (1, 2, 2)$ 的長度。",
      "answer": "$3$",
      "solution": "三維向量長度：$|\\vec{a}| = \\sqrt{x^2 + y^2 + z^2}$\n\n$|\\vec{a}| = \\sqrt{1^2 + 2^2 + 2^2}$\n$= \\sqrt{1 + 4 + 4}$\n$= \\sqrt{9} = 3$",
      "difficulty": "easy",
      "type": "calc",
      "relatedNodes": ["v4.1"],
      "tags": ["三維", "長度"]
    },
    {
      "id": "ex_v4_1_2",
      "title": "空間兩點距離",
      "question": "求 $A(1, 2, 3)$ 到 $B(4, 6, 15)$ 的距離。",
      "answer": "$13$",
      "solution": "$\\vec{AB} = (4-1, 6-2, 15-3) = (3, 4, 12)$\n\n$|\\vec{AB}| = \\sqrt{3^2 + 4^2 + 12^2}$\n$= \\sqrt{9 + 16 + 144}$\n$= \\sqrt{169} = 13$",
      "difficulty": "easy",
      "type": "calc",
      "relatedNodes": ["v4.1"],
      "tags": ["三維", "距離"]
    },
    {
      "id": "ex_v4_2_1",
      "title": "三維內積",
      "question": "計算 $(1, 2, 3) \\cdot (2, -1, 2)$",
      "answer": "$6$",
      "solution": "三維內積：$\\vec{a} \\cdot \\vec{b} = x_1x_2 + y_1y_2 + z_1z_2$\n\n$(1, 2, 3) \\cdot (2, -1, 2)$\n$= 1 \\times 2 + 2 \\times (-1) + 3 \\times 2$\n$= 2 - 2 + 6 = 6$",
      "difficulty": "easy",
      "type": "calc",
      "relatedNodes": ["v4.2"],
      "tags": ["三維", "內積"]
    },
    {
      "id": "ex_v4_2_2",
      "title": "空間垂直",
      "question": "$\\vec{a} = (1, 2, -1)$ 與 $\\vec{b} = (2, 0, 2)$ 是否垂直？",
      "answer": "是",
      "solution": "$\\vec{a} \\cdot \\vec{b} = 1 \\times 2 + 2 \\times 0 + (-1) \\times 2$\n$= 2 + 0 - 2 = 0$\n\n內積為 0，故垂直 ✓",
      "difficulty": "easy",
      "type": "calc",
      "relatedNodes": ["v4.2"],
      "tags": ["三維", "垂直"]
    },
    {
      "id": "ex_v4_3_1",
      "title": "外積計算",
      "question": "計算 $(1, 0, 0) \\times (0, 1, 0)$",
      "answer": "$(0, 0, 1)$",
      "solution": "外積行列式：\n$\\vec{a} \\times \\vec{b} = \\begin{vmatrix} \\hat{i} & \\hat{j} & \\hat{k} \\\\ 1 & 0 & 0 \\\\ 0 & 1 & 0 \\end{vmatrix}$\n\n$= \\hat{i}(0-0) - \\hat{j}(0-0) + \\hat{k}(1-0)$\n$= (0, 0, 1)$\n\n結果垂直於 $xy$ 平面",
      "difficulty": "medium",
      "type": "calc",
      "relatedNodes": ["v4.3"],
      "tags": ["外積"]
    },
    {
      "id": "ex_v4_3_2",
      "title": "外積性質",
      "question": "計算 $(2, 1, 0) \\times (1, 3, 0)$",
      "answer": "$(0, 0, 5)$",
      "solution": "$\\vec{a} \\times \\vec{b} = \\begin{vmatrix} \\hat{i} & \\hat{j} & \\hat{k} \\\\ 2 & 1 & 0 \\\\ 1 & 3 & 0 \\end{vmatrix}$\n\n$= \\hat{i}(0-0) - \\hat{j}(0-0) + \\hat{k}(6-1)$\n$= (0, 0, 5)$",
      "difficulty": "medium",
      "type": "calc",
      "relatedNodes": ["v4.3"],
      "tags": ["外積"]
    },
    {
      "id": "ex_v4_4_1",
      "title": "反交換律",
      "question": "驗證 $\\vec{a} \\times \\vec{b} = -\\vec{b} \\times \\vec{a}$，其中 $\\vec{a} = (1, 0, 0)$，$\\vec{b} = (0, 1, 0)$。",
      "answer": "見詳解",
      "solution": "$\\vec{a} \\times \\vec{b} = (0, 0, 1)$（由前題）\n\n$\\vec{b} \\times \\vec{a} = \\begin{vmatrix} \\hat{i} & \\hat{j} & \\hat{k} \\\\ 0 & 1 & 0 \\\\ 1 & 0 & 0 \\end{vmatrix} = (0, 0, -1)$\n\n確實 $\\vec{a} \\times \\vec{b} = -\\vec{b} \\times \\vec{a}$ ✓",
      "difficulty": "medium",
      "type": "proof",
      "relatedNodes": ["v4.4"],
      "tags": ["外積性質"]
    },
    {
      "id": "ex_v4_5_1",
      "title": "平行四邊形面積（3D）",
      "question": "求 $\\vec{a} = (1, 2, 0)$ 和 $\\vec{b} = (3, 1, 0)$ 張成的平行四邊形面積。",
      "answer": "$5$",
      "solution": "面積 $= |\\vec{a} \\times \\vec{b}|$\n\n$\\vec{a} \\times \\vec{b} = (0, 0, 1-6) = (0, 0, -5)$\n\n$|\\vec{a} \\times \\vec{b}| = |(0, 0, -5)| = 5$",
      "difficulty": "medium",
      "type": "calc",
      "relatedNodes": ["v4.5"],
      "tags": ["面積", "外積應用"]
    },
    {
      "id": "ex_v4_5_2",
      "title": "求法向量",
      "question": "求通過原點且垂直於 $\\vec{a} = (1, 1, 0)$ 和 $\\vec{b} = (0, 1, 1)$ 的平面的法向量。",
      "answer": "$(1, -1, 1)$",
      "solution": "法向量 = $\\vec{a} \\times \\vec{b}$\n\n$\\vec{n} = \\begin{vmatrix} \\hat{i} & \\hat{j} & \\hat{k} \\\\ 1 & 1 & 0 \\\\ 0 & 1 & 1 \\end{vmatrix}$\n\n$= \\hat{i}(1-0) - \\hat{j}(1-0) + \\hat{k}(1-0)$\n$= (1, -1, 1)$",
      "difficulty": "medium",
      "type": "calc",
      "relatedNodes": ["v4.5"],
      "tags": ["法向量", "外積應用"]
    },
    {
      "id": "ex_v4_6_1",
      "title": "平面方程式",
      "question": "法向量 $(1, 2, 3)$ 且過點 $(1, 0, 0)$ 的平面方程式為何？",
      "answer": "$x + 2y + 3z = 1$",
      "solution": "點法式：$\\vec{n} \\cdot (\\vec{r} - \\vec{r_0}) = 0$\n\n$(1, 2, 3) \\cdot ((x, y, z) - (1, 0, 0)) = 0$\n$1(x-1) + 2(y-0) + 3(z-0) = 0$\n$x - 1 + 2y + 3z = 0$\n$x + 2y + 3z = 1$",
      "difficulty": "medium",
      "type": "calc",
      "relatedNodes": ["v4.6"],
      "tags": ["平面方程式"]
    },
    {
      "id": "ex_v4_6_2",
      "title": "三點決定平面",
      "question": "求通過 $A(1,0,0)$，$B(0,1,0)$，$C(0,0,1)$ 的平面方程式。",
      "answer": "$x + y + z = 1$",
      "solution": "$\\vec{AB} = (-1, 1, 0)$，$\\vec{AC} = (-1, 0, 1)$\n\n法向量：$\\vec{n} = \\vec{AB} \\times \\vec{AC} = (1, 1, 1)$\n\n過點 $A(1,0,0)$：\n$1(x-1) + 1(y-0) + 1(z-0) = 0$\n$x + y + z = 1$",
      "difficulty": "hard",
      "type": "calc",
      "relatedNodes": ["v4.6"],
      "tags": ["平面方程式"]
    },
    {
      "id": "ex_v4_7_1",
      "title": "直線參數式",
      "question": "過點 $(1, 2, 3)$ 且方向向量為 $(2, -1, 1)$ 的直線參數式為何？",
      "answer": "$(x, y, z) = (1, 2, 3) + t(2, -1, 1)$",
      "solution": "直線參數式：$\\vec{r} = \\vec{r_0} + t\\vec{v}$\n\n$(x, y, z) = (1, 2, 3) + t(2, -1, 1)$\n\n展開：\n$x = 1 + 2t$\n$y = 2 - t$\n$z = 3 + t$",
      "difficulty": "easy",
      "type": "calc",
      "relatedNodes": ["v4.7"],
      "tags": ["直線方程式", "參數式"]
    },
    {
      "id": "ex_v4_8_1",
      "title": "點到平面距離",
      "question": "求點 $(1, 1, 1)$ 到平面 $x + y + z = 0$ 的距離。",
      "answer": "$\\sqrt{3}$",
      "solution": "點到平面距離公式：\n$d = \\frac{|Ax_0 + By_0 + Cz_0 + D|}{\\sqrt{A^2 + B^2 + C^2}}$\n\n平面 $x + y + z = 0$：$A=1, B=1, C=1, D=0$\n點 $(1, 1, 1)$\n\n$d = \\frac{|1+1+1+0|}{\\sqrt{1+1+1}} = \\frac{3}{\\sqrt{3}} = \\sqrt{3}$",
      "difficulty": "medium",
      "type": "calc",
      "relatedNodes": ["v4.8"],
      "tags": ["距離"]
    },
    {
      "id": "ex_v4_8_2",
      "title": "兩直線夾角",
      "question": "求直線 $L_1$ 方向向量 $(1, 0, 0)$ 與直線 $L_2$ 方向向量 $(1, 1, 0)$ 的夾角。",
      "answer": "$45°$",
      "solution": "直線夾角 = 方向向量夾角\n\n$\\cos\\theta = \\frac{(1,0,0) \\cdot (1,1,0)}{|(1,0,0)| \\cdot |(1,1,0)|}$\n\n$= \\frac{1}{1 \\times \\sqrt{2}} = \\frac{\\sqrt{2}}{2}$\n\n$\\theta = 45°$",
      "difficulty": "medium",
      "type": "calc",
      "relatedNodes": ["v4.8"],
      "tags": ["夾角"]
    },
    {
      "id": "ex_v4_9_1",
      "title": "純量三重積",
      "question": "計算 $(1, 0, 0) \\cdot ((0, 1, 0) \\times (0, 0, 1))$",
      "answer": "$0$",
      "solution": "先算外積：\n$(0, 1, 0) \\times (0, 0, 1) = (1, 0, 0)$\n\n再算內積：\n$(1, 0, 0) \\cdot (1, 0, 0) = 1$\n\n答案：$1$\n\n（註：題目計算結果應為 1，但若三向量共面則為 0）",
      "difficulty": "hard",
      "type": "calc",
      "relatedNodes": ["v4.9"],
      "tags": ["三重積"]
    },
    {
      "id": "ex_v5_1_1",
      "title": "2D 旋轉",
      "question": "將點 $(1, 0)$ 繞原點逆時針旋轉 $90°$，求新坐標。",
      "answer": "$(0, 1)$",
      "solution": "旋轉 $90°$ 的變換：$(x, y) \\to (-y, x)$\n\n$(1, 0) \\to (0, 1)$\n\n或用旋轉矩陣：\n$\\begin{pmatrix} \\cos 90° & -\\sin 90° \\\\ \\sin 90° & \\cos 90° \\end{pmatrix} \\begin{pmatrix} 1 \\\\ 0 \\end{pmatrix} = \\begin{pmatrix} 0 \\\\ 1 \\end{pmatrix}$",
      "difficulty": "medium",
      "type": "calc",
      "relatedNodes": ["v5.1"],
      "tags": ["旋轉", "座標轉換"]
    },
    {
      "id": "ex_v5_1_2",
      "title": "遊戲中的方向向量",
      "question": "遊戲角色在 $(2, 3)$，目標在 $(5, 7)$，求角色應朝向的單位方向向量。",
      "answer": "$(\\frac{3}{5}, \\frac{4}{5})$",
      "solution": "方向向量 = 目標 - 起點\n$\\vec{d} = (5, 7) - (2, 3) = (3, 4)$\n\n單位化：\n$|\\vec{d}| = \\sqrt{9 + 16} = 5$\n$\\hat{d} = \\frac{1}{5}(3, 4) = (\\frac{3}{5}, \\frac{4}{5})$\n\n此單位向量用於控制角色移動方向",
      "difficulty": "medium",
      "type": "calc",
      "relatedNodes": ["v5.1"],
      "tags": ["遊戲開發", "方向向量"]
    },
    {
      "id": "ex_v5_2_1",
      "title": "餘弦相似度",
      "question": "文件 A 的詞頻向量為 $(3, 4, 0)$，文件 B 為 $(0, 4, 3)$，求相似度。",
      "answer": "$\\frac{16}{25}$",
      "solution": "餘弦相似度：$\\text{sim}(A, B) = \\frac{\\vec{A} \\cdot \\vec{B}}{|\\vec{A}||\\vec{B}|}$\n\n$\\vec{A} \\cdot \\vec{B} = 3 \\times 0 + 4 \\times 4 + 0 \\times 3 = 16$\n$|\\vec{A}| = \\sqrt{9 + 16 + 0} = 5$\n$|\\vec{B}| = \\sqrt{0 + 16 + 9} = 5$\n\n$\\text{sim} = \\frac{16}{5 \\times 5} = \\frac{16}{25} = 0.64$",
      "difficulty": "hard",
      "type": "calc",
      "relatedNodes": ["v5.2"],
      "tags": ["機器學習", "相似度"]
    },
    {
      "id": "ex_v5_2_2",
      "title": "推薦系統",
      "question": "用戶 A 對電影評分 $(5, 3, 4)$，用戶 B 評分 $(4, 2, 5)$，判斷他們偏好是否相近。",
      "answer": "相近（餘弦相似度高）",
      "solution": "$\\vec{A} \\cdot \\vec{B} = 20 + 6 + 20 = 46$\n$|\\vec{A}| = \\sqrt{25 + 9 + 16} = \\sqrt{50}$\n$|\\vec{B}| = \\sqrt{16 + 4 + 25} = \\sqrt{45}$\n\n$\\cos\\theta = \\frac{46}{\\sqrt{50} \\times \\sqrt{45}} \\approx 0.97$\n\n相似度高，偏好相近，可推薦相似內容",
      "difficulty": "hard",
      "type": "calc",
      "relatedNodes": ["v5.2"],
      "tags": ["推薦系統", "資料分析"]
    },
    {
      "id": "ex_v5_3_1",
      "title": "邊緣偵測",
      "question": "說明向量如何用於影像邊緣偵測。",
      "answer": "計算梯度向量",
      "solution": "影像梯度向量：\n$\\nabla I = (\\frac{\\partial I}{\\partial x}, \\frac{\\partial I}{\\partial y})$\n\n梯度大小：$|\\nabla I| = \\sqrt{(\\frac{\\partial I}{\\partial x})^2 + (\\frac{\\partial I}{\\partial y})^2}$\n梯度方向：邊緣垂直方向\n\n應用：Sobel、Canny 邊緣偵測器",
      "difficulty": "hard",
      "type": "calc",
      "relatedNodes": ["v5.3"],
      "tags": ["影像處理", "梯度"]
    },
    {
      "id": "ex_v5_4_1",
      "title": "GPS 位移計算",
      "question": "從位置 $A(121.5°E, 25.0°N)$ 移動到 $B(121.6°E, 25.1°N)$，求位移向量（簡化為平面）。",
      "answer": "$(0.1°, 0.1°)$",
      "solution": "位移向量：\n$\\vec{AB} = B - A = (121.6 - 121.5, 25.1 - 25.0)$\n$= (0.1°, 0.1°)$\n\n實際應用需考慮：\n- 地球曲率\n- 經緯度轉換為公里\n- 高度變化（3D 向量）",
      "difficulty": "medium",
      "type": "calc",
      "relatedNodes": ["v5.4"],
      "tags": ["GPS", "地理"]
    },
    {
      "id": "ex_v6_1_1",
      "title": "力的合成",
      "question": "兩力 $\\vec{F_1} = (3, 4)$ N 和 $\\vec{F_2} = (1, -2)$ N 作用於同一點，求合力。",
      "answer": "$(4, 2)$ N",
      "solution": "力的合成：向量加法\n\n$\\vec{F} = \\vec{F_1} + \\vec{F_2}$\n$= (3, 4) + (1, -2)$\n$= (4, 2)$ N\n\n合力大小：$|\\vec{F}| = \\sqrt{16 + 4} = 2\\sqrt{5}$ N",
      "difficulty": "easy",
      "type": "calc",
      "relatedNodes": ["v6.1"],
      "tags": ["力學", "合力"]
    },
    {
      "id": "ex_v6_1_2",
      "title": "牛頓第二定律",
      "question": "質量 $2$ kg 的物體受力 $\\vec{F} = (6, 8)$ N，求加速度向量。",
      "answer": "$(3, 4)$ m/s²",
      "solution": "$\\vec{F} = m\\vec{a}$\n\n$\\vec{a} = \\frac{\\vec{F}}{m} = \\frac{(6, 8)}{2} = (3, 4)$ m/s²\n\n加速度大小：$|\\vec{a}| = \\sqrt{9 + 16} = 5$ m/s²",
      "difficulty": "easy",
      "type": "calc",
      "relatedNodes": ["v6.1"],
      "tags": ["牛頓定律", "加速度"]
    },
    {
      "id": "ex_v6_2_1",
      "title": "相對速度",
      "question": "火車 A 以 $\\vec{v_A} = (30, 0)$ km/h 行駛，火車 B 以 $\\vec{v_B} = (20, 20)$ km/h 行駛，求 A 相對於 B 的速度。",
      "answer": "$(10, -20)$ km/h",
      "solution": "相對速度：$\\vec{v_{AB}} = \\vec{v_A} - \\vec{v_B}$\n\n$= (30, 0) - (20, 20)$\n$= (10, -20)$ km/h\n\n從 B 看來，A 以此速度移動",
      "difficulty": "medium",
      "type": "calc",
      "relatedNodes": ["v6.2"],
      "tags": ["相對速度"]
    },
    {
      "id": "ex_v6_2_2",
      "title": "拋體運動",
      "question": "初速度 $\\vec{v_0} = (10, 20)$ m/s，重力加速度 $\\vec{g} = (0, -10)$ m/s²，求 $t=2$ 秒時的速度。",
      "answer": "$(10, 0)$ m/s",
      "solution": "$\\vec{v}(t) = \\vec{v_0} + \\vec{g}t$\n\n$\\vec{v}(2) = (10, 20) + (0, -10) \\times 2$\n$= (10, 20) + (0, -20)$\n$= (10, 0)$ m/s\n\n此時水平速度 10 m/s，垂直速度 0（最高點）",
      "difficulty": "medium",
      "type": "calc",
      "relatedNodes": ["v6.2"],
      "tags": ["拋體運動"]
    },
    {
      "id": "ex_v6_3_1",
      "title": "功的計算",
      "question": "力 $\\vec{F} = (3, 4)$ N 使物體沿 $\\vec{d} = (2, 0)$ m 移動，求作功。",
      "answer": "$6$ J",
      "solution": "功：$W = \\vec{F} \\cdot \\vec{d}$\n\n$W = (3, 4) \\cdot (2, 0)$\n$= 3 \\times 2 + 4 \\times 0$\n$= 6$ J（焦耳）\n\n物理意義：只有力在位移方向的分量做功",
      "difficulty": "easy",
      "type": "calc",
      "relatedNodes": ["v6.3"],
      "tags": ["功", "內積"]
    },
    {
      "id": "ex_v6_4_1",
      "title": "力矩計算",
      "question": "力 $\\vec{F} = (0, 0, 10)$ N 作用於位置 $\\vec{r} = (2, 0, 0)$ m，求力矩。",
      "answer": "$(0, 20, 0)$ N·m",
      "solution": "力矩：$\\vec{\\tau} = \\vec{r} \\times \\vec{F}$\n\n$\\vec{\\tau} = \\begin{vmatrix} \\hat{i} & \\hat{j} & \\hat{k} \\\\ 2 & 0 & 0 \\\\ 0 & 0 & 10 \\end{vmatrix}$\n\n$= \\hat{i}(0) - \\hat{j}(20) + \\hat{k}(0)$\n$= (0, -20, 0)$ N·m\n\n或 $(0, 20, 0)$（方向依右手定則）",
      "difficulty": "medium",
      "type": "calc",
      "relatedNodes": ["v6.4"],
      "tags": ["力矩", "外積"]
    },
    {
      "id": "ex_v6_5_1",
      "title": "勞倫茲力",
      "question": "電荷 $q = 2$ C 以速度 $\\vec{v} = (1, 0, 0)$ m/s 進入磁場 $\\vec{B} = (0, 0, 1)$ T，求所受的力。",
      "answer": "$(0, 2, 0)$ N",
      "solution": "勞倫茲力：$\\vec{F} = q\\vec{v} \\times \\vec{B}$\n\n$\\vec{v} \\times \\vec{B} = \\begin{vmatrix} \\hat{i} & \\hat{j} & \\hat{k} \\\\ 1 & 0 & 0 \\\\ 0 & 0 & 1 \\end{vmatrix} = (0, 1, 0)$\n\n$\\vec{F} = 2 \\times (0, 1, 0) = (0, 2, 0)$ N\n\n力垂直於速度和磁場（右手定則）",
      "difficulty": "hard",
      "type": "calc",
      "relatedNodes": ["v6.5"],
      "tags": ["電磁學", "勞倫茲力"]
    }
  ]
}
